multissh/__init__.py
multissh/connection.py
multissh/mssh.py
multissh/utils.py
multissh-0.1.5.data/scripts/mssh
multissh-0.1.5.dist-info/LICENSE
multissh-0.1.5.dist-info/METADATA
multissh-0.1.5.dist-info/WHEEL
multissh-0.1.5.dist-info/top_level.txt
multissh-0.1.5.dist-info/RECORD
