Metadata-Version: 2.1
Name: multissh
Version: 0.1.5
Summary: Tool to connect to multiple SSH servers and broadcast commands.
Home-page: https://github.com/JaanPorkon/MultiSSH
Author: Jaan Porkon
Author-email: jaantrill@gmail.com
License: UNKNOWN
Platform: UNKNOWN
Classifier: Programming Language :: Python :: 3
Classifier: License :: OSI Approved :: MIT License
Classifier: Operating System :: OS Independent
Requires-Python: >=3.6
Requires-Dist: requests
Requires-Dist: paramiko
Requires-Dist: tldextract
